AUTHORS.md
INSTALL.md
LICENSE.txt
MANIFEST.in
README.md
README.rst
release_checklist.md
requirements.txt
setup.cfg
setup.py
docs/Makefile
docs/boreholes.rst
docs/building.rst
docs/conf.py
docs/index.rst
docs/make.bat
docs/metadata.rst
docs/utilities.rst
docs/vocabulary.rst
docs/webservices.rst
docs/sphinxext/apigen.py
docs/sphinxext/docscrape.py
docs/sphinxext/docscrape_sphinx.py
docs/sphinxext/inheritance_diagram.py
docs/sphinxext/ipython_console_highlighting.py
docs/sphinxext/numpydoc.py
pysiss/__init__.py
pysiss.egg-info/PKG-INFO
pysiss.egg-info/SOURCES.txt
pysiss.egg-info/dependency_links.txt
pysiss.egg-info/requires.txt
pysiss.egg-info/top_level.txt
pysiss/borehole/__init__.py
pysiss/borehole/borehole.py
pysiss/borehole/details.py
pysiss/borehole/plotting.py
pysiss/borehole/analysis/__init__.py
pysiss/borehole/analysis/detrend.py
pysiss/borehole/analysis/regularizer.py
pysiss/borehole/datasets/__init__.py
pysiss/borehole/datasets/dataset.py
pysiss/borehole/datasets/interval_dataset.py
pysiss/borehole/datasets/point_dataset.py
pysiss/borehole/properties/__init__.py
pysiss/borehole/properties/property.py
pysiss/borehole/properties/property_type.py
pysiss/borehole/siss/__init__.py
pysiss/borehole/siss/borehole_generator.py
pysiss/coverage/__init__.py
pysiss/coverage/raster.py
pysiss/coverage/vector.py
pysiss/metadata/__init__.py
pysiss/metadata/metadata.py
pysiss/metadata/registry.py
pysiss/utilities/__init__.py
pysiss/utilities/collection.py
pysiss/utilities/id_object.py
pysiss/utilities/maths.py
pysiss/utilities/projection.py
pysiss/utilities/singleton.py
pysiss/vocabulary/__init__.py
pysiss/vocabulary/namespaces.py
pysiss/vocabulary/unmarshal.py
pysiss/vocabulary/erml/__init__.py
pysiss/vocabulary/erml/unmarshallers.py
pysiss/vocabulary/gml/__init__.py
pysiss/vocabulary/gml/unmarshallers.py
pysiss/vocabulary/gsml/__init__.py
pysiss/vocabulary/gsml/unmarshallers.py
pysiss/vocabulary/resources/__init__.py
pysiss/vocabulary/resources/__init__.pyc
pysiss/vocabulary/resources/namespaces.json
pysiss/webservices/__init__.py
pysiss/webservices/geoscience_australia_geology.py
pysiss/webservices/nvcl.py
